wingrab/__init__.py
wingrab/__main__.py
wingrab/cursor.cur
wingrab/wingrab.py
WinGrab-0.0.2.dist-info/LICENSE
WinGrab-0.0.2.dist-info/METADATA
WinGrab-0.0.2.dist-info/WHEEL
WinGrab-0.0.2.dist-info/entry_points.txt
WinGrab-0.0.2.dist-info/top_level.txt
WinGrab-0.0.2.dist-info/RECORD
