Metadata-Version: 2.1
Name: WinGrab
Version: 0.0.2
Summary: WinGrab: A simple tool to get the PID of the window under the cursor.
Home-page: https://github.com/JezaChen/WinGrab
Author: Jianzhang Chen
Author-email: jezachen@163.com
License: MIT
Keywords: win32api windows gui
Classifier: Development Status :: 3 - Alpha
Classifier: Intended Audience :: Developers
Classifier: Operating System :: Microsoft :: Windows
Classifier: Programming Language :: Python :: 3.7
Classifier: Programming Language :: Python :: 3.8
Classifier: Programming Language :: Python :: 3.9
Classifier: Programming Language :: Python :: 3.10
Classifier: Programming Language :: Python :: 3.11
Classifier: Programming Language :: Python :: 3.12
Classifier: Programming Language :: Python :: 3.13
Classifier: Development Status :: 4 - Beta
Classifier: License :: OSI Approved :: MIT License
Requires-Python: >=3.7, <4
License-File: LICENSE
